cooka/__init__.py
cooka/_version.py
cooka/cli.py
cooka/cooka_config.py.template
cooka/server.py
cooka/assets/10.async.js
cooka/assets/11.async.js
cooka/assets/12.async.js
cooka/assets/13.async.js
cooka/assets/2.async.js
cooka/assets/2.chunk.css
cooka/assets/3.async.js
cooka/assets/3.chunk.css
cooka/assets/4.async.js
cooka/assets/4.chunk.css
cooka/assets/5.async.js
cooka/assets/5.chunk.css
cooka/assets/6.async.js
cooka/assets/7.async.js
cooka/assets/8.async.js
cooka/assets/9.async.js
cooka/assets/index.html
cooka/assets/umi.css
cooka/assets/umi.js
cooka/assets/vendors.async.js
cooka/assets/vendors.chunk.css
cooka/assets/static/logo.59d748d2.png
cooka/common/__init__.py
cooka/common/authentication.py
cooka/common/client.py
cooka/common/consts.py
cooka/common/dataset_util.py
cooka/common/exceptions.py
cooka/common/i18n.py
cooka/common/log.py
cooka/common/model.py
cooka/common/serializer.py
cooka/common/util.py
cooka/core/__init__.py
cooka/core/analyze_correlation_job.py
cooka/core/analyze_job.py
cooka/core/analyzer.py
cooka/core/batch_predict_job.py
cooka/core/dask_analyzer.py
cooka/core/evaluator.py
cooka/core/process_manager.py
cooka/core/train_code_generator.py
cooka/core/train_job.py
cooka/core/train_template/evaluate_binary_classification.jinja2
cooka/core/train_template/evaluate_multi_classification.jinja2
cooka/core/train_template/evaluate_regression.jinja2
cooka/core/train_template/macro.jinja2
cooka/core/train_template/plot_confusion_matrix.jinja2
cooka/core/train_template/plot_feature_importance.jinja2
cooka/core/train_template/plot_roc_curve.jinja2
cooka/core/train_template/search_dt.jinja2
cooka/core/train_template/search_gbm.jinja2
cooka/core/train_template/target_raw_python.jinja2
cooka/core/train_template/train_config.jinja2
cooka/core/train_template/train_data_partition.jinja2
cooka/core/train_template/train_evaluate.jinja2
cooka/core/train_template/train_header.jinja2
cooka/core/train_template/train_persist.jinja2
cooka-0.1.5.dist-info/LICENSE
cooka-0.1.5.dist-info/METADATA
cooka-0.1.5.dist-info/WHEEL
cooka-0.1.5.dist-info/entry_points.txt
cooka-0.1.5.dist-info/top_level.txt
cooka-0.1.5.dist-info/RECORD
