Metadata-Version: 2.1
Name: cooka
Version: 0.1.5
Summary: A lightweight AutoML system.
Home-page: UNKNOWN
Author: DataCanvas Community
Author-email: yangjian@zetyun.com
License: Apache License 2.0
Platform: Linux
Platform: Mac OS X
Classifier: Operating System :: OS Independent
Classifier: Intended Audience :: Developers
Classifier: Intended Audience :: Education
Classifier: Intended Audience :: Science/Research
Classifier: Programming Language :: Python
Classifier: Programming Language :: Python :: 3.6
Classifier: Programming Language :: Python :: 3.7
Classifier: Topic :: Scientific/Engineering
Classifier: Topic :: Scientific/Engineering :: Artificial Intelligence
Classifier: Topic :: Software Development
Classifier: Topic :: Software Development :: Libraries
Classifier: Topic :: Software Development :: Libraries :: Python Modules
Classifier: License :: OSI Approved :: Apache Software License
Requires-Python: >=3.6.*
License-File: LICENSE
Requires-Dist: numpy
Requires-Dist: pandas
Requires-Dist: scikit-learn (>=0.22.1)
Requires-Dist: requests
Requires-Dist: SQLAlchemy (>=1.3.18)
Requires-Dist: tornado (==6.0.4)
Requires-Dist: jinja2
Requires-Dist: deeptables (==0.1.13)
Requires-Dist: hypergbm (==0.2.2)
Requires-Dist: traitlets
